ROrgPr_ws_15/Arbeitsverzeichnis/Yolowsky/Blatt06/reg.vhd
library ieee;
use ieee.std_logic_1164.all;
use ieee.numeric_std.all;

entity reg is
	generic(
		WIDTH : integer);
	port(
		clk : in  std_logic;
		rst : in  std_logic;
		en  : in  std_logic;
		D   : in  std_logic_vector( WIDTH - 1 downto 0 );
		Q   : out std_logic_vector( WIDTH - 1 downto 0 ));
end reg;

architecture behavioral of reg is
begin
	process (clk)
	begin
		if (clk = '1' and clk'event) then
			if(rst = '1') then
				Q <= (others => '0');
			elsif (en = '1') then
				Q <= D;
			end if;
		end if;
	end process;
	
end behavioral;

ROrgPr_ws_15/Arbeitsverzeichnis/Yolowsky/Blatt06/reg_tb.vhd
library ieee;
use ieee.std_logic_1164.all;

library std;
use std.textio.all;

entity reg_tb is
end reg_tb;

architecture behavioral of reg_tb is

	signal clk, en, rst :std_logic := '0';
	constant WIDTH : integer := 32;
	signal D, Q : std_logic_vector(WIDTH - 1 downto 0);
	signal sim_stop : boolean := false;
	
begin

	CLK_GEN: process
	begin
		if sim_stop then
			wait;
		end if;
		clk <= not clk;
		wait for 5 ns;
	end process;
	
	REG: entity work.reg(behavioral)
		generic map(
			WIDTH => WIDTH)
		port map(
			clk => clk,
			rst => rst,
			en => en,
			D => D,
			Q => Q);

	TESTBENCH: process
		variable points : integer := 2;
		variable resetNotWorking : boolean := false;
		variable l : line;
	begin
	
		-- check for synchronous reset functionality
		wait for 2 ns; -- 2ns
		rst <= '1';
		wait for 2 ns; -- 4ns
		if Q = x"00000000" then
			write(l, time'image(now));
			write(l, string'(": Das Register hat ein asynchrones reset-Signal."));
			writeline(OUTPUT, l);
			points := points - 1;
		else
			wait for 7 ns; -- 11ns
			if Q /= x"00000000" then
				write(l, time'image(now));
				write(l, string'(": Das reset-Signal hat keinen Einfluss auf das Register."));
				writeline(OUTPUT, l);
				points := points - 1;
				resetNotWorking := true;
			end if;
		end if;
		wait for 15 ns - now;
		rst <= '0';
		
		-- check functionality of the enable signal
		en <= '0';
		D <= (others => '1');
		wait for 6 ns; -- 21ns
		if Q = x"FFFFFFFF" then
			write(l, time'image(now));
			write(l, string'(": Trotz nichtgesetztem enable-Signal wird das Register beschrieben."));
			writeline(OUTPUT, l);
			points := points - 1;
		else
			en <= '1';
			wait for 10 ns; -- 31ns
			if Q /= x"FFFFFFFF" then
				write(l, time'image(now));
				write(l, string'(": Das Register wird bei gesetztem enable-Signal nicht korrekt beschrieben."));
				writeline(OUTPUT, l);
				points := points - 1;
			end if;
		end if;
		wait for 35 ns - now;
		
		-- check if reset has higher priority than common write
		if not resetNotWorking then
			rst <= '1';
			en <= '1';
			D <= x"AAAA5555";
			wait for 6 ns; -- 41ns
			if Q /= x"00000000" then
				write(l, time'image(now));
				write(l, string'(": Das reset-Signal hat eine niedrigere Prioritaet als ein gewoehnlicher Schreibzugriff."));
				writeline(OUTPUT, l);
				if points > 0 then
					points := points - 1;
				end if;
			else
				rst <= '0';
				wait for 10 ns; -- 51ns
				if Q /= x"AAAA5555" then
					write(l, time'image(now));
					write(l, string'(": Gewoehnlicher Schreibzugriff fehlgeschlagen."));
					writeline(OUTPUT, l);
					if points > 0 then
						points := points - 1;
					end if;
				end if;
			end if;
		end if;
		rst <= '0';
		en <= '0';
		
		-- evaluation
		wait for 60 ns - now;
		
		if points = 2 then
			report "Das Register funktioniert einwandfrei! (reg: 2/2 Punkte)" severity note;
		else
			report "Das Register funktioniert nicht einwandfrei! (reg: "& integer'image(points) & "/2 Punkte)" severity failure;
		end if;
		
		sim_stop <= true;
		wait;
	end process;
	
end behavioral;

ROrgPr_ws_15/Arbeitsverzeichnis/Yolowsky/Blatt06/vsim/reg_tb.vcd
$date
	Tue Dec  8 15:41:43 2015
$end
$version
	ModelSim Version 6.6d
$end
$timescale
	1ps
$end
$scope module reg_tb $end
$var wire 1 ! clk $end
$var wire 1 " en $end
$var wire 1 # rst $end
$var wire 1 $ d [31] $end
$var wire 1 % d [30] $end
$var wire 1 & d [29] $end
$var wire 1 ' d [28] $end
$var wire 1 ( d [27] $end
$var wire 1 ) d [26] $end
$var wire 1 * d [25] $end
$var wire 1 + d [24] $end
$var wire 1 , d [23] $end
$var wire 1 - d [22] $end
$var wire 1 . d [21] $end
$var wire 1 / d [20] $end
$var wire 1 0 d [19] $end
$var wire 1 1 d [18] $end
$var wire 1 2 d [17] $end
$var wire 1 3 d [16] $end
$var wire 1 4 d [15] $end
$var wire 1 5 d [14] $end
$var wire 1 6 d [13] $end
$var wire 1 7 d [12] $end
$var wire 1 8 d [11] $end
$var wire 1 9 d [10] $end
$var wire 1 : d [9] $end
$var wire 1 ; d [8] $end
$var wire 1 < d [7] $end
$var wire 1 = d [6] $end
$var wire 1 > d [5] $end
$var wire 1 ? d [4] $end
$var wire 1 @ d [3] $end
$var wire 1 A d [2] $end
$var wire 1 B d [1] $end
$var wire 1 C d [0] $end
$var wire 1 D q [31] $end
$var wire 1 E q [30] $end
$var wire 1 F q [29] $end
$var wire 1 G q [28] $end
$var wire 1 H q [27] $end
$var wire 1 I q [26] $end
$var wire 1 J q [25] $end
$var wire 1 K q [24] $end
$var wire 1 L q [23] $end
$var wire 1 M q [22] $end
$var wire 1 N q [21] $end
$var wire 1 O q [20] $end
$var wire 1 P q [19] $end
$var wire 1 Q q [18] $end
$var wire 1 R q [17] $end
$var wire 1 S q [16] $end
$var wire 1 T q [15] $end
$var wire 1 U q [14] $end
$var wire 1 V q [13] $end
$var wire 1 W q [12] $end
$var wire 1 X q [11] $end
$var wire 1 Y q [10] $end
$var wire 1 Z q [9] $end
$var wire 1 [ q [8] $end
$var wire 1 \ q [7] $end
$var wire 1 ] q [6] $end
$var wire 1 ^ q [5] $end
$var wire 1 _ q [4] $end
$var wire 1 ` q [3] $end
$var wire 1 a q [2] $end
$var wire 1 b q [1] $end
$var wire 1 c q [0] $end
$scope module reg $end
$var wire 1 ! clk $end
$var wire 1 # rst $end
$var wire 1 " en $end
$var wire 1 $ d [31] $end
$var wire 1 % d [30] $end
$var wire 1 & d [29] $end
$var wire 1 ' d [28] $end
$var wire 1 ( d [27] $end
$var wire 1 ) d [26] $end
$var wire 1 * d [25] $end
$var wire 1 + d [24] $end
$var wire 1 , d [23] $end
$var wire 1 - d [22] $end
$var wire 1 . d [21] $end
$var wire 1 / d [20] $end
$var wire 1 0 d [19] $end
$var wire 1 1 d [18] $end
$var wire 1 2 d [17] $end
$var wire 1 3 d [16] $end
$var wire 1 4 d [15] $end
$var wire 1 5 d [14] $end
$var wire 1 6 d [13] $end
$var wire 1 7 d [12] $end
$var wire 1 8 d [11] $end
$var wire 1 9 d [10] $end
$var wire 1 : d [9] $end
$var wire 1 ; d [8] $end
$var wire 1 < d [7] $end
$var wire 1 = d [6] $end
$var wire 1 > d [5] $end
$var wire 1 ? d [4] $end
$var wire 1 @ d [3] $end
$var wire 1 A d [2] $end
$var wire 1 B d [1] $end
$var wire 1 C d [0] $end
$var wire 1 D q [31] $end
$var wire 1 E q [30] $end
$var wire 1 F q [29] $end
$var wire 1 G q [28] $end
$var wire 1 H q [27] $end
$var wire 1 I q [26] $end
$var wire 1 J q [25] $end
$var wire 1 K q [24] $end
$var wire 1 L q [23] $end
$var wire 1 M q [22] $end
$var wire 1 N q [21] $end
$var wire 1 O q [20] $end
$var wire 1 P q [19] $end
$var wire 1 Q q [18] $end
$var wire 1 R q [17] $end
$var wire 1 S q [16] $end
$var wire 1 T q [15] $end
$var wire 1 U q [14] $end
$var wire 1 V q [13] $end
$var wire 1 W q [12] $end
$var wire 1 X q [11] $end
$var wire 1 Y q [10] $end
$var wire 1 Z q [9] $end
$var wire 1 [ q [8] $end
$var wire 1 \ q [7] $end
$var wire 1 ] q [6] $end
$var wire 1 ^ q [5] $end
$var wire 1 _ q [4] $end
$var wire 1 ` q [3] $end
$var wire 1 a q [2] $end
$var wire 1 b q [1] $end
$var wire 1 c q [0] $end
$upscope $end
$upscope $end
$enddefinitions $end
#0
$dumpvars
1!
0"
0#
x$
x%
x&
x'
x(
x)
x*
x+
x,
x-
x.
x/
x0
x1
x2
x3
x4
x5
x6
x7
x8
x9
x:
x;
x<
x=
x>
x?
x@
xA
xB
xC
xD
xE
xF
xG
xH
xI
xJ
xK
xL
xM
xN
xO
xP
xQ
xR
xS
xT
xU
xV
xW
xX
xY
xZ
x[
x\
x]
x^
x_
x`
xa
xb
xc
$end
#2000
1#
#5000
0!
#10000
1!
0c
0b
0a
0`
0_
0^
0]
0\
0[
0Z
0Y
0X
0W
0V
0U
0T
0S
0R
0Q
0P
0O
0N
0M
0L
0K
0J
0I
0H
0G
0F
0E
0D
#15000
1C
1B
1A
1@
1?
1>
1=
1<
1;
1:
19
18
17
16
15
14
13
12
11
10
1/
1.
1-
1,
1+
1*
1)
1(
1'
1&
1%
1$
0#
0!
#20000
1!
#21000
1"
#25000
0!
#30000
1!
1c
1b
1a
1`
1_
1^
1]
1\
1[
1Z
1Y
1X
1W
1V
1U
1T
1S
1R
1Q
1P
1O
1N
1M
1L
1K
1J
1I
1H
1G
1F
1E
1D
#35000
0B
0@
0>
0<
0:
08
06
04
03
01
0/
0-
0+
0)
0'
0%
1#
0!
#40000
1!
0c
0b
0a
0`
0_
0^
0]
0\
0[
0Z
0Y
0X
0W
0V
0U
0T
0S
0R
0Q
0P
0O
0N
0M
0L
0K
0J
0I
0H
0G
0F
0E
0D
#41000
0#
#45000
0!
#50000
1!
1c
1a
1_
1]
1[
1Y
1W
1U
1R
1P
1N
1L
1J
1H
1F
1D
#51000
0"
